[{"class_name": "pedestrian", "bbox": "359 69 389 151", "used": true}, {"class_name": "pedestrian", "bbox": "37 149 87 252", "used": true}, {"class_name": "pedestrian", "bbox": "256 103 291 194", "used": true}, {"class_name": "pedestrian", "bbox": "688 181 727 295", "used": true}, {"class_name": "pedestrian", "bbox": "740 192 782 308", "used": true}, {"class_name": "pedestrian", "bbox": "791 209 837 330", "used": true}, {"class_name": "pedestrian", "bbox": "438 248 482 380", "used": true}, {"class_name": "pedestrian", "bbox": "489 17 514 85", "used": true}, {"class_name": "pedestrian", "bbox": "826 212 874 334", "used": true}, {"class_name": "pedestrian", "bbox": "531 17 555 85", "used": true}, {"class_name": "pedestrian", "bbox": "484 7 507 73", "used": false}, {"class_name": "pedestrian", "bbox": "30 204 86 321", "used": true}, {"class_name": "pedestrian", "bbox": "30 314 97 461", "used": true}, {"class_name": "pedestrian", "bbox": "359 69 389 151", "used": false}, {"class_name": "pedestrian", "bbox": "37 149 87 252", "used": false}, {"class_name": "pedestrian", "bbox": "256 103 291 194", "used": false}, {"class_name": "pedestrian", "bbox": "688 181 727 295", "used": false}, {"class_name": "pedestrian", "bbox": "740 192 782 308", "used": false}, {"class_name": "pedestrian", "bbox": "791 209 837 330", "used": false}, {"class_name": "pedestrian", "bbox": "438 248 482 380", "used": false}, {"class_name": "pedestrian", "bbox": "489 17 514 85", "used": false}, {"class_name": "pedestrian", "bbox": "826 212 874 334", "used": false}, {"class_name": "pedestrian", "bbox": "531 17 555 85", "used": false}, {"class_name": "pedestrian", "bbox": "484 7 507 73", "used": false}, {"class_name": "pedestrian", "bbox": "30 204 86 321", "used": false}, {"class_name": "pedestrian", "bbox": "30 314 97 461", "used": false}, {"class_name": "pedestrian", "bbox": "359 69 389 151", "used": false}, {"class_name": "pedestrian", "bbox": "37 149 87 252", "used": false}, {"class_name": "pedestrian", "bbox": "256 103 291 194", "used": false}, {"class_name": "pedestrian", "bbox": "688 181 727 295", "used": false}, {"class_name": "pedestrian", "bbox": "740 192 782 308", "used": false}, {"class_name": "pedestrian", "bbox": "791 209 837 330", "used": false}, {"class_name": "pedestrian", "bbox": "438 248 482 380", "used": false}, {"class_name": "pedestrian", "bbox": "489 17 514 85", "used": false}, {"class_name": "pedestrian", "bbox": "826 212 874 334", "used": false}, {"class_name": "pedestrian", "bbox": "531 17 555 85", "used": false}, {"class_name": "pedestrian", "bbox": "484 7 507 73", "used": false}, {"class_name": "pedestrian", "bbox": "30 204 86 321", "used": false}, {"class_name": "pedestrian", "bbox": "30 314 97 461", "used": false}, {"class_name": "pedestrian", "bbox": "359 69 389 151", "used": false}, {"class_name": "pedestrian", "bbox": "37 149 87 252", "used": false}, {"class_name": "pedestrian", "bbox": "256 103 291 194", "used": false}, {"class_name": "pedestrian", "bbox": "688 181 727 295", "used": false}, {"class_name": "pedestrian", "bbox": "740 192 782 308", "used": false}, {"class_name": "pedestrian", "bbox": "791 209 837 330", "used": false}, {"class_name": "pedestrian", "bbox": "438 248 482 380", "used": false}, {"class_name": "pedestrian", "bbox": "489 17 514 85", "used": false}, {"class_name": "pedestrian", "bbox": "826 212 874 334", "used": false}, {"class_name": "pedestrian", "bbox": "531 17 555 85", "used": false}, {"class_name": "pedestrian", "bbox": "484 7 507 73", "used": false}, {"class_name": "pedestrian", "bbox": "30 204 86 321", "used": false}, {"class_name": "pedestrian", "bbox": "30 314 97 461", "used": false}, {"class_name": "pedestrian", "bbox": "359 69 389 151", "used": false}, {"class_name": "pedestrian", "bbox": "37 149 87 252", "used": false}, {"class_name": "pedestrian", "bbox": "256 103 291 194", "used": false}, {"class_name": "pedestrian", "bbox": "688 181 727 295", "used": false}, {"class_name": "pedestrian", "bbox": "740 192 782 308", "used": false}, {"class_name": "pedestrian", "bbox": "791 209 837 330", "used": false}, {"class_name": "pedestrian", "bbox": "438 248 482 380", "used": false}, {"class_name": "pedestrian", "bbox": "489 17 514 85", "used": false}, {"class_name": "pedestrian", "bbox": "826 212 874 334", "used": false}, {"class_name": "pedestrian", "bbox": "531 17 555 85", "used": false}, {"class_name": "pedestrian", "bbox": "484 7 507 73", "used": false}, {"class_name": "pedestrian", "bbox": "30 204 86 321", "used": false}, {"class_name": "pedestrian", "bbox": "30 314 97 461", "used": false}, {"class_name": "pedestrian", "bbox": "359 69 389 151", "used": false}, {"class_name": "pedestrian", "bbox": "37 149 87 252", "used": false}, {"class_name": "pedestrian", "bbox": "256 103 291 194", "used": false}, {"class_name": "pedestrian", "bbox": "688 181 727 295", "used": false}, {"class_name": "pedestrian", "bbox": "740 192 782 308", "used": false}, {"class_name": "pedestrian", "bbox": "791 209 837 330", "used": false}, {"class_name": "pedestrian", "bbox": "438 248 482 380", "used": false}, {"class_name": "pedestrian", "bbox": "489 17 514 85", "used": false}, {"class_name": "pedestrian", "bbox": "826 212 874 334", "used": false}, {"class_name": "pedestrian", "bbox": "531 17 555 85", "used": false}, {"class_name": "pedestrian", "bbox": "484 7 507 73", "used": false}, {"class_name": "pedestrian", "bbox": "30 204 86 321", "used": false}, {"class_name": "pedestrian", "bbox": "30 314 97 461", "used": false}, {"class_name": "pedestrian", "bbox": "359 69 389 151", "used": false}, {"class_name": "pedestrian", "bbox": "37 149 87 252", "used": false}, {"class_name": "pedestrian", "bbox": "256 103 291 194", "used": false}, {"class_name": "pedestrian", "bbox": "688 181 727 295", "used": false}, {"class_name": "pedestrian", "bbox": "740 192 782 308", "used": false}, {"class_name": "pedestrian", "bbox": "791 209 837 330", "used": false}, {"class_name": "pedestrian", "bbox": "438 248 482 380", "used": false}, {"class_name": "pedestrian", "bbox": "489 17 514 85", "used": false}, {"class_name": "pedestrian", "bbox": "826 212 874 334", "used": false}, {"class_name": "pedestrian", "bbox": "531 17 555 85", "used": false}, {"class_name": "pedestrian", "bbox": "484 7 507 73", "used": false}, {"class_name": "pedestrian", "bbox": "30 204 86 321", "used": false}, {"class_name": "pedestrian", "bbox": "30 314 97 461", "used": false}, {"class_name": "pedestrian", "bbox": "359 69 389 151", "used": false}, {"class_name": "pedestrian", "bbox": "37 149 87 252", "used": false}, {"class_name": "pedestrian", "bbox": "256 103 291 194", "used": false}, {"class_name": "pedestrian", "bbox": "688 181 727 295", "used": false}, {"class_name": "pedestrian", "bbox": "740 192 782 308", "used": false}, {"class_name": "pedestrian", "bbox": "791 209 837 330", "used": false}, {"class_name": "pedestrian", "bbox": "438 248 482 380", "used": false}, {"class_name": "pedestrian", "bbox": "489 17 514 85", "used": false}, {"class_name": "pedestrian", "bbox": "826 212 874 334", "used": false}, {"class_name": "pedestrian", "bbox": "531 17 555 85", "used": false}, {"class_name": "pedestrian", "bbox": "484 7 507 73", "used": false}, {"class_name": "pedestrian", "bbox": "30 204 86 321", "used": false}, {"class_name": "pedestrian", "bbox": "30 314 97 461", "used": false}, {"class_name": "pedestrian", "bbox": "359 69 389 151", "used": false}, {"class_name": "pedestrian", "bbox": "37 149 87 252", "used": false}, {"class_name": "pedestrian", "bbox": "256 103 291 194", "used": false}, {"class_name": "pedestrian", "bbox": "688 181 727 295", "used": false}, {"class_name": "pedestrian", "bbox": "740 192 782 308", "used": false}, {"class_name": "pedestrian", "bbox": "791 209 837 330", "used": false}, {"class_name": "pedestrian", "bbox": "438 248 482 380", "used": false}, {"class_name": "pedestrian", "bbox": "489 17 514 85", "used": false}, {"class_name": "pedestrian", "bbox": "826 212 874 334", "used": false}, {"class_name": "pedestrian", "bbox": "531 17 555 85", "used": false}, {"class_name": "pedestrian", "bbox": "484 7 507 73", "used": false}, {"class_name": "pedestrian", "bbox": "30 204 86 321", "used": false}, {"class_name": "pedestrian", "bbox": "30 314 97 461", "used": false}, {"class_name": "pedestrian", "bbox": "359 69 389 151", "used": false}, {"class_name": "pedestrian", "bbox": "37 149 87 252", "used": false}, {"class_name": "pedestrian", "bbox": "256 103 291 194", "used": false}, {"class_name": "pedestrian", "bbox": "688 181 727 295", "used": false}, {"class_name": "pedestrian", "bbox": "740 192 782 308", "used": false}, {"class_name": "pedestrian", "bbox": "791 209 837 330", "used": false}, {"class_name": "pedestrian", "bbox": "438 248 482 380", "used": false}, {"class_name": "pedestrian", "bbox": "489 17 514 85", "used": false}, {"class_name": "pedestrian", "bbox": "826 212 874 334", "used": false}, {"class_name": "pedestrian", "bbox": "531 17 555 85", "used": false}, {"class_name": "pedestrian", "bbox": "484 7 507 73", "used": false}, {"class_name": "pedestrian", "bbox": "30 204 86 321", "used": false}, {"class_name": "pedestrian", "bbox": "30 314 97 461", "used": false}, {"class_name": "pedestrian", "bbox": "359 69 389 151", "used": false}, {"class_name": "pedestrian", "bbox": "37 149 87 252", "used": false}, {"class_name": "pedestrian", "bbox": "256 103 291 194", "used": false}, {"class_name": "pedestrian", "bbox": "688 181 727 295", "used": false}, {"class_name": "pedestrian", "bbox": "740 192 782 308", "used": false}, {"class_name": "pedestrian", "bbox": "791 209 837 330", "used": false}, {"class_name": "pedestrian", "bbox": "438 248 482 380", "used": false}, {"class_name": "pedestrian", "bbox": "489 17 514 85", "used": false}, {"class_name": "pedestrian", "bbox": "826 212 874 334", "used": false}, {"class_name": "pedestrian", "bbox": "531 17 555 85", "used": false}, {"class_name": "pedestrian", "bbox": "484 7 507 73", "used": false}, {"class_name": "pedestrian", "bbox": "30 204 86 321", "used": false}, {"class_name": "pedestrian", "bbox": "30 314 97 461", "used": false}, {"class_name": "pedestrian", "bbox": "359 69 389 151", "used": false}, {"class_name": "pedestrian", "bbox": "37 149 87 252", "used": false}, {"class_name": "pedestrian", "bbox": "256 103 291 194", "used": false}, {"class_name": "pedestrian", "bbox": "688 181 727 295", "used": false}, {"class_name": "pedestrian", "bbox": "740 192 782 308", "used": false}, {"class_name": "pedestrian", "bbox": "791 209 837 330", "used": false}, {"class_name": "pedestrian", "bbox": "438 248 482 380", "used": false}, {"class_name": "pedestrian", "bbox": "489 17 514 85", "used": false}, {"class_name": "pedestrian", "bbox": "826 212 874 334", "used": false}, {"class_name": "pedestrian", "bbox": "531 17 555 85", "used": false}, {"class_name": "pedestrian", "bbox": "484 7 507 73", "used": false}, {"class_name": "pedestrian", "bbox": "30 204 86 321", "used": false}, {"class_name": "pedestrian", "bbox": "30 314 97 461", "used": false}, {"class_name": "pedestrian", "bbox": "359 69 389 151", "used": false}, {"class_name": "pedestrian", "bbox": "37 149 87 252", "used": false}, {"class_name": "pedestrian", "bbox": "256 103 291 194", "used": false}, {"class_name": "pedestrian", "bbox": "688 181 727 295", "used": false}, {"class_name": "pedestrian", "bbox": "740 192 782 308", "used": false}, {"class_name": "pedestrian", "bbox": "791 209 837 330", "used": false}, {"class_name": "pedestrian", "bbox": "438 248 482 380", "used": false}, {"class_name": "pedestrian", "bbox": "489 17 514 85", "used": false}, {"class_name": "pedestrian", "bbox": "826 212 874 334", "used": false}, {"class_name": "pedestrian", "bbox": "531 17 555 85", "used": false}, {"class_name": "pedestrian", "bbox": "484 7 507 73", "used": false}, {"class_name": "pedestrian", "bbox": "30 204 86 321", "used": false}, {"class_name": "pedestrian", "bbox": "30 314 97 461", "used": false}, {"class_name": "pedestrian", "bbox": "359 69 389 151", "used": false}, {"class_name": "pedestrian", "bbox": "37 149 87 252", "used": false}, {"class_name": "pedestrian", "bbox": "256 103 291 194", "used": false}, {"class_name": "pedestrian", "bbox": "688 181 727 295", "used": false}, {"class_name": "pedestrian", "bbox": "740 192 782 308", "used": false}, {"class_name": "pedestrian", "bbox": "791 209 837 330", "used": false}, {"class_name": "pedestrian", "bbox": "438 248 482 380", "used": false}, {"class_name": "pedestrian", "bbox": "489 17 514 85", "used": false}, {"class_name": "pedestrian", "bbox": "826 212 874 334", "used": false}, {"class_name": "pedestrian", "bbox": "531 17 555 85", "used": false}, {"class_name": "pedestrian", "bbox": "484 7 507 73", "used": false}, {"class_name": "pedestrian", "bbox": "30 204 86 321", "used": false}, {"class_name": "pedestrian", "bbox": "30 314 97 461", "used": false}]